{
	"author": {
		"name": "Matthew Prince",
		"url": "https://blog.cloudflare.com/author/matthew-prince/",
		"sameAs": [
			"https://twitter.com/eastdakota"
		]
	},
	"headline": "vpn首选 - 具有Warp技术的移动端1.1.1.1 dns应用程序，Cloudflare免费vpn，更高速、更私密",
	"url": "https://blog.cloudflare.com/zh-cn/1111-warp-better-vpn-zh-cn/",
	"datePublished": "2019-04-01T13:00:00.000Z",
	"dateModified": "2021-01-28T18:51:30.000Z",
	"image": "https://blog.cloudflare.com/content/images/2019/09/main-warp-share-1.png",
	"keywords": "WARP (CN), 简体中文 (CN), 产品新闻, 1.1.1.1 (CN), VPN (CN), DNS (CN)",
	"description": "4月1日对大多数互联网用户来说是一个悲惨的日子。尽管大多数时候互联网充满希望和创新，但在“愚人节”这天，少数几家顶尖科技公司决定浪费数十亿人的时间，讲一些只有他们自己才觉得好笑的幼稚笑话。"
}