{
	"author": {
		"name": "Matthew Prince",
		"url": "https://blog.cloudflare.com/author/matthew-prince/",
		"sameAs": [
			"https://twitter.com/eastdakota"
		]
	},
	"headline": "hCaptcha替代reCAPTCHA_国内如何使用reCAPTCHA_Cloudflare变更验证码服务",
	"url": "https://blog.cloudflare.com/zh-cn/moving-from-recaptcha-to-hcaptcha-zh-cn/",
	"datePublished": "2020-04-08T13:00:00.000Z",
	"dateModified": "2021-01-28T20:01:25.000Z",
	"image": "http://blog.cloudflare.com/content/images/2020/11/image3-5-1.png",
	"keywords": "简体中文 (CN), 製品ニュース (JP), hCaptcha (ZH), 速度和可靠性 (CN)",
	"description": "最近，我们将使用的CAPTCHA 提供商从 Google 的 reCAPTCHA 迁移到了独立机构 hCaptcha 提供的服务。我们对此项变动感到兴奋，因为它有助于解决因为依赖 Google 服务而固有的隐私问题（已经存在一段时间）"
}