{
	"name": "@cylution/is-cloudflare-ip",
	"description": "check if request IP come from Cloudflare",
	"version": "1.0.0",
	"date": "2021-09-06T16:23:04.115Z",
	"links": {
		"homepage": "https://github.com/cylution-org/is-cloudflare-ip#readme",
		"repository": "git+https://github.com/cylution-org/is-cloudflare-ip.git",
		"bugs": "https://github.com/cylution-org/is-cloudflare-ip/issues",
		"npm": "https://www.npmjs.com/package/@cylution/is-cloudflare-ip"
	},
	"tags": {
		"latest": {
			"version": "1.0.0",
			"date": "2021-09-06T16:23:04.115Z"
		}
	}
}