{
	"name": "gql2ts",
	"description": "Convert GraphQL Schema to TypeScript defs",
	"version": "1.10.1",
	"date": "2018-09-25T19:54:26.935Z",
	"links": {
		"homepage": "https://github.com/avantcredit/gql2ts#readme",
		"repository": "git+https://github.com/avantcredit/gql2ts.git",
		"bugs": "https://github.com/avantcredit/gql2ts/issues",
		"npm": "https://www.npmjs.com/package/gql2ts"
	},
	"tags": {
		"latest": {
			"version": "1.10.1",
			"date": "2018-09-25T19:54:26.935Z"
		},
		"canary": {
			"version": "1.9.0-alpha.5ddac749",
			"date": "2018-06-06T18:41:24.836Z"
		},
		"next": {
			"version": "2.0.0-3",
			"date": "2018-11-28T22:04:17.409Z"
		}
	}
}