{
	"author": {
		"name": "Garrett Galow",
		"url": "https://blog.cloudflare.com/author/garrett/",
		"sameAs": []
	},
	"headline": "Perubahan Konfigurasi Versi dan Tahap dengan Aplikasi HTTP dalam Beta",
	"url": "https://blog.cloudflare.com/id-id/version-and-stage-configuration-changes-with-http-applications-in-beta-id-id/",
	"datePublished": "2021-12-11T13:59:00.000Z",
	"dateModified": "2021-12-31T05:49:26.000Z",
	"image": "http://blog.cloudflare.com/content/images/2021/12/image7-9-1.png",
	"keywords": "CIO Week (ID), Indonesia",
	"description": "Hari ini, kami mengumumkan beta tertutup Aplikasi HTTP: cara baru untuk menguji dan memberlakukan perubahan pada lalu lintas HTTP Anda dengan aman. Aplikasi HTTP memperkenalkan penetapan versi konfigurasi dan kemampuan kontrol saat"
}