{
	"author": {
		"name": "Aran Garcia (G11N)",
		"url": "http://blog.cloudflare.com/author/aran/",
		"sameAs": []
	},
	"headline": "世界で最も相互接続性の高いネットワークで、リアルタイムのオーディオビデオアプリを構築する",
	"url": "http://blog.cloudflare.com/ja-jp/announcing-cloudflare-calls-ja-jp/",
	"datePublished": "2022-09-27T13:00:00.000Z",
	"dateModified": "2022-09-27T14:52:53.000Z",
	"image": "http://blog.cloudflare.com/content/images/2022/09/Cloudflare-Calls-1-2.png",
	"keywords": "Birthday Week (JP), Cloudflare Calls (JP), WebRTC (JP), Video Calls (JP), Japanese (JP)",
	"description": "開発者がリアルタイムのオーディオ/ビデオアプリケーションを構築できる新製品を発表します"
}