{
	"@context": "https://schema.org",
	"@type": "Article",
	"publisher": {
		"@type": "Organization",
		"name": "The Cloudflare Blog",
		"logo": {
			"@type": "ImageObject",
			"url": "https://blog-cloudflare-com-assets.storage.googleapis.com/2019/06/logo-cloudflare-dark-1.svg",
			"width": 109,
			"height": 40.5
		}
	},
	"author": {
		"@type": "Person",
		"name": "Romain Aviolat (Guest Blogger)",
		"image": {
			"@type": "ImageObject",
			"url": "http://blog.cloudflare.com/content/images/2021/12/romain_aviolat.png",
			"width": 200,
			"height": 200
		},
		"url": "https://blog.cloudflare.com/author/romain-aviolat/",
		"sameAs": [
			"https://kudelskisecurity.com/"
		]
	},
	"headline": "ゲストブログ：KUDELSKI SECURITY社とK8Sトンネル",
	"url": "https://blog.cloudflare.com/ja-jp/guest-blog-zero-trust-access-kubernetes-ja-jp/",
	"datePublished": "2021-12-08T13:59:00.000Z",
	"dateModified": "2021-12-30T00:54:09.000Z",
	"image": {
		"@type": "ImageObject",
		"url": "http://blog.cloudflare.com/content/images/2021/12/image4-12-3.png",
		"width": 1200,
		"height": 675
	},
	"keywords": "ゼロトラスト, CIO Week (JP), Cloudflare Access (JP), Cloudflare Tunnel (JP), 日本語",
	"description": "本日は、マネージドセキュリティ・サービス・プロバイダーのKudelski Security社の友人によって書かれたブログ記事を公開します。数週間前、Kudelski Security社の主席クラウドおよびセキュリティエンジニアであるRomain Aviolat氏は、リモートワー",
	"mainEntityOfPage": {
		"@type": "WebPage",
		"@id": "http://blog.cloudflare.com/"
	}
}