{
	"author": {
		"name": "Jon Rolfe",
		"url": "https://blog.cloudflare.com/author/jon-rolfe/",
		"sameAs": [
			"https://twitter.com/jrolfoid"
		]
	},
	"headline": "Cloudflare Passes 250 Cities, Triples External Network Capacity, 8x-es Backbone",
	"url": "https://blog.cloudflare.com/250-cities-is-just-the-start/",
	"datePublished": "2021-09-13T12:59:02.000Z",
	"dateModified": "2021-09-18T14:20:46.000Z",
	"image": "http://blog.cloudflare.com/content/images/2021/09/image2-9.png",
	"keywords": "Speed Week, Cloudflare Network, Internet Performance",
	"description": "Today, I have three speedy infrastructure updates: we’ve passed 250 on-network cities, more than tripled our external network capacity, and increased our long-haul internal backbone network by over 800% since the start of 2020."
}