{
	"initialReadingTime": "9",
	"locale": "en-us",
	"post": {
		"authors": [
			{
				"name": "Sergi Isasi",
				"slug": "sergi"
			},
			{
				"name": "Vicky Shrestha",
				"slug": "vicky"
			}
		],
		"excerpt": "Cloudflare first started talking about DNSSEC in 2014 and at the time, Nick Sullivan wrote: “DNSSEC is a valuable tool for improving the trust and integrity of DNS, the backbone of the modern Internet.”",
		"feature_image": "https://blog.cloudflare.com/_emdash/api/media/file/01KW46GJK9DAHY8SATJWBPMYPY.png",
		"published_at": "2018-09-18T13:00:00.000Z",
		"slug": "automatically-provision-and-maintain-dnssec",
		"tags": [
			{
				"name": "Crypto Week",
				"slug": "crypto-week"
			},
			{
				"name": "Cryptography",
				"slug": "cryptography"
			},
			{
				"name": "DNS",
				"slug": "dns"
			},
			{
				"name": "DNSSEC",
				"slug": "dnssec"
			},
			{
				"name": "Product News",
				"slug": "product-news"
			},
			{
				"name": "Reliability",
				"slug": "reliability"
			},
			{
				"name": "Security",
				"slug": "security"
			}
		],
		"title": "Expanding DNSSEC Adoption",
		"updated_at": "2026-07-15T13:07:08.790Z",
		"url": "https://blog.cloudflare.com/automatically-provision-and-maintain-dnssec/"
	}
}