{
	"author": {
		"name": "Alissa Starzak",
		"url": "https://blog.cloudflare.com/author/alissa-starzak/",
		"sameAs": []
	},
	"headline": "How to Build a Global Network that Complies with Local Law",
	"url": "https://blog.cloudflare.com/global-network-that-complies-with-local-law/",
	"datePublished": "2020-12-11T12:00:00.000Z",
	"dateModified": "2020-12-11T12:00:01.000Z",
	"image": "http://blog.cloudflare.com/content/images/2020/12/image2-33.png",
	"keywords": "Privacy Week, Legal",
	"description": "Running a global network that complies with different privacy laws around the world requires coming back to the values that we have championed since our founding."
}