{
	"author": {
		"name": "Omer Yoachimik",
		"url": "http://blog.cloudflare.com/author/omer/",
		"sameAs": [
			"https://twitter.com/OmerYoahimik"
		]
	},
	"headline": "Introducing Cloudflare’s new Network Analytics dashboard",
	"url": "http://blog.cloudflare.com/network-analytics-v2-announcement/",
	"datePublished": "2023-04-12T13:49:14.000Z",
	"dateModified": "2023-09-20T15:25:23.000Z",
	"image": "http://blog.cloudflare.com/content/images/2023/04/image6-2.png",
	"keywords": "DDoS, Magic Transit, Spectrum, Product News",
	"description": "Learn how the new and improved Network Analytics dashboard provides security professionals insights into their DDoS attack and traffic landscape"
}