{
	"author": {
		"name": "John Graham-Cumming",
		"url": "http://blog.cloudflare.com/author/john-graham-cumming/",
		"sameAs": []
	},
	"headline": "Writing poems using LLama 2 on Workers AI",
	"url": "http://blog.cloudflare.com/writing-poems-using-llama-2-on-workers-ai/",
	"datePublished": "2023-09-27T13:00:36.000Z",
	"dateModified": "2023-10-30T15:17:56.000Z",
	"image": "http://blog.cloudflare.com/content/images/2023/09/image1-31.png",
	"keywords": "Birthday Week, AI, Workers AI, Cloudflare Workers",
	"description": "Matthew and Michelle, co-founders of Cloudflare, published their annual founders’ letter today. The letter ends with a poem written by an AI running using Workers AI on Cloudflare’s global network. \n\nHere’s the code that wrote the poem"
}